tremors/__init__.py
tremors/collector.py
tremors/decorator.py
tremors/logger.py
tremors/py.typed
tremors-0.4.0.dist-info/licenses/LICENSE
tremors-0.4.0.dist-info/METADATA
tremors-0.4.0.dist-info/WHEEL
tremors-0.4.0.dist-info/top_level.txt
tremors-0.4.0.dist-info/RECORD
