Metadata-Version: 2.4
Name: tremors
Version: 0.4.0
Summary: Tremors is a library for logging while collecting metrics.
Author-email: Narvin Singh <Narvin.A.Singh@gmail.com>
License: Tremors is a library for logging with metrics.
Project-URL: Homepage, https://tremors.readthedocs.io
Project-URL: Documentation, https://tremors.readthedocs.io
Project-URL: Repository, https://gitlab.com/narvin/tremors
Project-URL: Issues, https://gitlab.com/narvin/tremors/-/issues
Keywords: logging,log,logger,metrics
Classifier: Programming Language :: Python :: 3
Classifier: License :: OSI Approved :: GNU General Public License v3 or later (GPLv3+)
Classifier: Operating System :: OS Independent
Requires-Python: >=3.12
License-File: LICENSE
Provides-Extra: dev
Requires-Dist: mypy~=1.18; extra == "dev"
Requires-Dist: pre-commit~=4.3; extra == "dev"
Requires-Dist: pytest~=8.4; extra == "dev"
Requires-Dist: ruff~=0.14.2; extra == "dev"
Requires-Dist: sphinx-lint~=1.0; extra == "dev"
Requires-Dist: yamllint~=1.37; extra == "dev"
Provides-Extra: doc
Requires-Dist: python-docs-theme~=2025.10; extra == "doc"
Requires-Dist: sphinx~=8.2; extra == "doc"
Provides-Extra: deploy
Requires-Dist: build~=1.3; extra == "deploy"
Requires-Dist: twine~=6.2; extra == "deploy"
Dynamic: license-file
